ODDEP/public/chips/test/C74LS90.vhd
LIBRARY IEEE;
USE IEEE.STD_LOGIC_1164.ALL;
USE IEEE.STD_LOGIC_ARITH.ALL;
USE IEEE.STD_LOGIC_UNSIGNED.ALL;

ENTITY C74LS90 is
	port(
	port1:in std_logic;   --notCPb
	port2:in std_logic;   --R1
	port3:in std_logic;   --R2
	port4:in std_logic;   --NC
	port5:in std_logic;   --VCC 5v
	port6:in std_logic;   --S1
	port7:in std_logic;   --S2
	port8:out std_logic;  --Q2
	port9:out std_logic;  --Q1
	port11:out std_logic; --Q3
	port12:out std_logic; --Q0
	port10:in std_logic;  --GND
	port14:in std_logic;  --notCPa
	port13:in std_logic   --NC
);
END C74LS90;
architecture two OF C74LS90 IS
	signal q1: std_logic := '0';   --QA
	signal q2: std_logic_vector(2 downto 0) := "000";  --qD,QC,QB
BEGIN
	port12 <= q1;
	port11 <= q2(2);
	port8 <= q2(1);
	port9 <= q2(0);
	
	counter2: PROCESS(port14, port2, port3, port6, port7)
	begin
		if(port6='1' and port7='1')then -- S1 = '1' and S2 = '1'
			q1 <= '1';
			-- q2 <= "100";
		elsif (port2 = '1' and port3 = '1') then-- R1 = '1' and R2 = '1'
			q1 <= '0';
		elsif (port14'event and port14='0')then
			q1 <= not q1;
		end if;	
		
	end process;
	
	counter5: PROCESS(port1,port2,port3,port6,port7)
	begin
		if(port6='1' and port7='1')then
			q2<="100";		
		elsif(port2='1' and port3='1')then
			q2<="000";
		elsif(port1'event and port1='0')then
			case q2 is
				when "000" => q2 <= "001";
				when "001" => q2 <= "010";
				when "010" => q2 <= "011";
 				when "011" => q2 <= "100";
				when "100" => q2 <= "000";
				when others => q2 <= "000";
			end case;
			-- q2 <= q2 + 1;
			-- if q2 = "101" then
				-- q2 <= "000";
			-- end if;
		end if;
	end process;
end;

ODDEP/public/chips/test/testC74LS90.vhd
-- testbench of C74LS90
LIBRARY IEEE;
USE IEEE.STD_LOGIC_1164.ALL;
USE IEEE.STD_LOGIC_ARITH.ALL;
USE IEEE.STD_LOGIC_UNSIGNED.ALL;

entity test74ls90 is
end test74ls90;

architecture rtl of test74ls90 is
    component C74LS90 is
        port(
        port1:in std_logic;   --notCPb
        port2:in std_logic;   --R1
        port3:in std_logic;   --R2
        port4:in std_logic;   --NC
        port5:in std_logic;   --VCC 5v
        port6:in std_logic;   --S1
        port7:in std_logic;   --S2
        port8:out std_logic;  --Q2
        port9:out std_logic;  --Q1
        port11:out std_logic; --Q3
        port12:out std_logic; --Q0
        port10:in std_logic;  --GND
        port14:in std_logic;  --notCPa
        port13:in std_logic   --NC
        );
    end component;

    constant EMPTY : std_logic := '0';
    constant clk_period : time := 200 ps;
    signal clka, clkb : std_logic;
    signal R1, R2 : std_logic;
    signal S1, S2 : std_logic;
    signal Q : std_logic_vector(3 downto 0) := "0000";

begin
    u0_74ls90: C74LS90 port map (
        port1 => clkb,
        port2 => R1,
        port3 => R2,
        port4 => EMPTY,
        port5 => '1',
        port6 => S1,
        port7 => S2,
        port8 => Q(2),
        port9 => Q(1),
        port10 => '0',
        port11 => Q(3),
        port12 => Q(0),
        port13 => EMPTY,
        port14 => clka
    );

    R1 <= '0';
    R2 <= '0';
    S1 <= '0';
    S2 <= '0';

    clka_gen: process
    begin
        clka <= '0';
        wait for clk_period / 2;
        clka <= '1';
        wait for clk_period / 2;
    end process;

    clkb_gen: process
    begin
        clkb <= '0';
        wait for clk_period / 2;
        clkb <= '1';
        wait for clk_period / 2;
    end process;

end rtl;

public/chips/test/74ls90.vcd
$date
	Thu Nov 10 08:52:35 2016
$end
$version
	ModelSim Version 10.4d
$end
$timescale
	1ps
$end

$scope module test74ls90 $end
$var wire 1 ! clka $end
$var wire 1 " clkb $end
$var wire 1 # R1 $end
$var wire 1 $ R2 $end
$var wire 1 % S1 $end
$var wire 1 & S2 $end
$var wire 1 ' Q [3] $end
$var wire 1 ( Q [2] $end
$var wire 1 ) Q [1] $end
$var wire 1 * Q [0] $end
$upscope $end
$enddefinitions $end
#0
$dumpvars
0!
0"
0#
0$
0%
0&
0'
0(
1)
1*
$end
#100
1!
1"
#200
0!
0"
0*
0)
1(
#300
1!
1"
#400
0!
0"
1*
1)
#500
1!
1"
#600
0!
0"
0*
0)
0(
1'
#700
1!
1"
#800
0!
0"
1*
0'
#900
1!
1"
#1000
0!
0"
0*
1)
#1100
1!
1"
#1200
0!
0"
1*
0)
1(
#1300
1!
1"
#1400
0!
0"
0*
1)
#1500
1!
1"
#1600
0!
0"
1*
0)
0(
1'
#1700
1!
1"
#1800
0!
0"
0*
0'
#1900
1!
1"
#2000
0!
0"
1*
1)
#2100
1!
1"
#2200
0!
0"
0*
0)
1(
#2300
1!
1"
#2400
0!
0"
1*
1)
#2500
1!
1"
#2600
0!
0"
0*
0)
0(
1'
#2700
1!
1"
#2800
0!
0"
1*
0'
#2900
1!
1"
#3000
0!
0"
0*
1)
#3100
1!
1"
#3200
0!
0"
1*
0)
1(
#3300
1!
1"
#3400
0!
0"
0*
1)
#3500
1!
1"
#3600
0!
0"
1*
0)
0(
1'
#3700
1!
1"
#3800
0!
0"
0*
0'
#3900
1!
1"
#4000
0!
0"
1*
1)
