public/chips/test/C74LS161.vhd
LIBRARY IEEE;
USE IEEE.STD_LOGIC_1164.ALL;
USE IEEE.STD_LOGIC_ARITH.ALL;
USE IEEE.STD_LOGIC_UNSIGNED.ALL;

ENTITY C74LS161 is
	port(
	port1  : in  std_logic;   -- notR
	port2  : in  std_logic;   -- CP
	port3  : in  std_logic;   -- A
	port4  : in  std_logic;   -- B
	port5  : in  std_logic;   -- C
	port6  : in  std_logic;   -- D
	port7  : in  std_logic;   -- P, control signal
	port8  : in  std_logic;   -- GND
	port9  : in  std_logic;   -- notLD
	port10 : in  std_logic;   -- T, control signal
	port11 : out std_logic;   -- Q3
	port12 : out std_logic;   -- Q2
	port13 : out std_logic;   -- Q1
	port14 : out std_logic;   -- Q0
	port15 : out std_logic;   -- Co
	port16 : in  std_logic    -- Vcc 5V
);
END C74LS161;

ARCHITECTURE Behaviour OF C74LS161 IS
	
	constant EMPTY4 : std_logic_vector(3 downto 0) := "0000";
	signal Q:         std_logic_vector(3 downto 0) := "0000";
	signal tempCo :   std_logic := '0';
	
BEGIN
	port15 <= tempCo;
	port11 <= Q(3);
	port12 <= Q(2);
	port13 <= Q(1);
	port14 <= Q(0);

	count: PROCESS(port1, port2, port9, port7, port10, port3, port4, port5, port6)
	begin
		if(port1 = '1') then -- R = '0'
			tempCo <= '0';
			Q <= EMPTY4;
		elsif (port9 = '1' and (port10 = '0' or port7 = '0')) then 
		 	-- do nothing, keep Q
		elsif (port2'event and port2='1') then
			if (port9 = '1') then -- LD = '0'
				Q(0) <= port3; -- A
				Q(1) <= port4; -- B
				Q(2) <= port5; -- C
				Q(3) <= port6; -- D
			elsif (port7 = '1' and port10 = '1') then -- T = '1' and P = '1' (and LD = '1' and R = '1')
				case Q is
					when "1111" =>
						tempCo <= '1';
					when others =>
						tempCo <= '0';		
				end case;
				Q <= Q + 1;
			end if;
		end if;
	end process;

end Behaviour;

ODDEP/public/chips/test/testC74LS161.vhd
-- testbench of C74LS161.vhd

LIBRARY IEEE;
USE IEEE.STD_LOGIC_1164.ALL;
USE IEEE.STD_LOGIC_ARITH.ALL;
USE IEEE.STD_LOGIC_UNSIGNED.ALL;

entity testc74ls161 is
end testc74ls161;

architecture rtl of testc74ls161 is

component C74LS161 is
	port(
	port1  : in  std_logic;   -- notR
	port2  : in  std_logic;   -- CP
	port3  : in  std_logic;   -- A
	port4  : in  std_logic;   -- B
	port5  : in  std_logic;   -- C
	port6  : in  std_logic;   -- D
	port7  : in  std_logic;   -- P, control signal
	port8  : in  std_logic;   -- GND
	port9  : in  std_logic;   -- notLoad
	port10 : in  std_logic;   -- T, control signal
	port11 : out std_logic;   -- Q3
	port12 : out std_logic;   -- Q2
	port13 : out std_logic;   -- Q1
	port14 : out std_logic;   -- Q0
	port15 : out std_logic;   -- Co
	port16 : in  std_logic    -- Vcc 5V
);
end component;

    constant clk_period : time := 200 ps;
    constant EMPTY : std_logic := '0';

    signal notR, notLoad : std_logic := EMPTY;
    signal CP : std_logic := EMPTY;
    signal A, B, C, D : std_logic := EMPTY;
    signal P, T : std_logic := '1';
    signal Q : std_logic_vector(3 downto 0);
    signal Co : std_logic := EMPTY;

begin
    u0_74ls161 : C74LS161 port map (
        port1  => notR,
        port2  => CP,
        port3  => A,
        port4  => B,
        port5  => C,
        port6  => D,
        port7  => P,
        port8  => EMPTY,
        port9  => notLoad,
        port10 => T,
        port11 => Q(3),
        port12 => Q(2),
        port13 => Q(1),
        port14 => Q(0),
        port15 => Co,
        port16 => EMPTY
    );

    notR <= '0';
    notLoad <= '0';
    P <= '1';
    T <= '1';

    cp_gen: process
    begin
        CP <= '0';
        wait for clk_period / 2;
        CP <= '1';
        wait for clk_period / 2;
    end process;


end;

public/chips/test/74ls161.vcd
$date
	Thu Nov 10 08:47:25 2016
$end
$version
	ModelSim Version 10.4d
$end
$timescale
	1ps
$end

$scope module testc74ls161 $end
$var wire 1 ! notR $end
$var wire 1 " notLoad $end
$var wire 1 # CP $end
$var wire 1 $ A $end
$var wire 1 % B $end
$var wire 1 & C $end
$var wire 1 ' D $end
$var wire 1 ( P $end
$var wire 1 ) T $end
$var wire 1 * Q [3] $end
$var wire 1 + Q [2] $end
$var wire 1 , Q [1] $end
$var wire 1 - Q [0] $end
$var wire 1 . Co $end
$upscope $end
$enddefinitions $end
#0
$dumpvars
0!
0"
0#
0$
0%
0&
0'
1(
1)
0.
0*
0+
0,
0-
$end
#100
1#
#200
0#
#300
1#
#400
0#
#500
1#
#600
0#
#700
1#
#800
0#
#900
1#
#1000
0#
#1100
1#
#1200
0#
#1300
1#
#1400
0#
#1500
1#
#1600
0#
#1700
1#
#1800
0#
#1900
1#
#2000
0#
#2100
1#
#2200
0#
#2300
1#
#2400
0#
#2500
1#
#2600
0#
#2700
1#
#2800
0#
#2900
1#
#3000
0#
#3100
1#
#3200
0#
#3300
1#
#3400
0#
#3500
1#
#3600
0#
#3700
1#
#3800
0#
#3900
1#
#4000
0#
